bloodrecon/__init__.py
bloodrecon/__main__.py
bloodrecon/cli.py
bloodrecon/modules/__init__.py
bloodrecon/modules/asn_resolver.py
bloodrecon/modules/colors.py
bloodrecon/modules/common_crawl.py
bloodrecon/modules/directory_bruteforce.py
bloodrecon/modules/dns_lookup.py
bloodrecon/modules/doc_metadata.py
bloodrecon/modules/email_validator.py
bloodrecon/modules/exif_extractor.py
bloodrecon/modules/favicon_hash.py
bloodrecon/modules/github_intel.py
bloodrecon/modules/google_dorking.py
bloodrecon/modules/google_drive_leaks.py
bloodrecon/modules/http_headers.py
bloodrecon/modules/ip_lookup.py
bloodrecon/modules/ip_range_scanner.py
bloodrecon/modules/isp_tracker.py
bloodrecon/modules/js_endpoint_scanner.py
bloodrecon/modules/leak_search.py
bloodrecon/modules/maps_parser.py
bloodrecon/modules/pastebin_search.py
bloodrecon/modules/phone_intel.py
bloodrecon/modules/port_scanner.py
bloodrecon/modules/reverse_dns.py
bloodrecon/modules/robots_scanner.py
bloodrecon/modules/shodan_lookup.py
bloodrecon/modules/sitemap_parser.py
bloodrecon/modules/social_checker.py
bloodrecon/modules/ssl_scanner.py
bloodrecon/modules/subdomain_finder.py
bloodrecon/modules/tech_fingerprint.py
bloodrecon/modules/temp_email_checker.py
bloodrecon/modules/url_analyzer.py
bloodrecon/modules/useragent_detector.py
bloodrecon/modules/wayback_machine.py
bloodrecon/modules/whois_lookup.py
bloodrecon/modules/list-imp/common.txt
bloodrecon/modules/list-imp/temp_domains.txt
bloodrecon-1.2.1.dist-info/licenses/LICENSE
bloodrecon-1.2.1.dist-info/METADATA
bloodrecon-1.2.1.dist-info/WHEEL
bloodrecon-1.2.1.dist-info/entry_points.txt
bloodrecon-1.2.1.dist-info/top_level.txt
bloodrecon-1.2.1.dist-info/RECORD
