Metadata-Version: 2.4
Name: bloodrecon
Version: 1.2.1
Summary: Advanced OSINT Intelligence Framework for cybersecurity professionals
Author: Alex Butler - Vritra Security Organization
License: MIT
Project-URL: Homepage, https://github.com/VritraSecz/BloodRecon
Project-URL: Repository, https://github.com/VritraSecz/BloodRecon
Project-URL: Documentation, https://github.com/VritraSecz/BloodRecon/blob/main/README.md
Project-URL: Bug Reports, https://github.com/VritraSecz/BloodRecon/issues
Project-URL: Developer Website, https://vritrasec.com
Keywords: osint,reconnaissance,cybersecurity,intelligence,framework,penetration-testing
Classifier: Development Status :: 5 - Production/Stable
Classifier: Intended Audience :: Information Technology
Classifier: Intended Audience :: System Administrators
Classifier: License :: OSI Approved :: MIT License
Classifier: Operating System :: OS Independent
Classifier: Programming Language :: Python :: 3
Classifier: Programming Language :: Python :: 3.7
Classifier: Programming Language :: Python :: 3.8
Classifier: Programming Language :: Python :: 3.9
Classifier: Programming Language :: Python :: 3.10
Classifier: Programming Language :: Python :: 3.11
Classifier: Programming Language :: Python :: 3.12
Classifier: Topic :: Security
Classifier: Topic :: Internet :: WWW/HTTP
Classifier: Topic :: System :: Networking
Classifier: Topic :: System :: Systems Administration
Requires-Python: >=3.7
License-File: LICENSE
Requires-Dist: colorama==0.4.6
Requires-Dist: dnspython==2.7.0
Requires-Dist: mmh3==5.1.0
Requires-Dist: phonenumbers==9.0.10
Requires-Dist: Pillow==11.3.0
Requires-Dist: requests==2.32.4
Requires-Dist: shodan==1.31.0
Requires-Dist: urllib3==2.5.0
Requires-Dist: whois==1.20240129.2
Dynamic: license-file
